setup.py
infdent/__init__.py
infdent.egg-info/PKG-INFO
infdent.egg-info/SOURCES.txt
infdent.egg-info/dependency_links.txt
infdent.egg-info/not-zip-safe
infdent.egg-info/top_level.txt