Metadata-Version: 1.0
Name: infdent
Version: 1.0
Summary: A helpful utility for quickly creating well formatted text for quick reading.
Home-page: https://github.com/Jackojc/infdent
Author: Jack Clarke
Author-email: jackojc@gmail.com
License: MIT
Platform: UNKNOWN
